<LexicalEntry>
	<feat att="partOfSpeech" val="commonNoun" />
	<feat att="id" val="GMU_BANAN_1" />
	<feat att="morphologicalUnitId" val="BANAN" />
	<feat att="originalSource" val="PAROLE" />
	<feat att="independentWord" val="yes" />
	<Lemma>
		<FormRepresentation>
			<feat att="writtenForm" val="banan" />
			<feat att="officiallyApproved" val="yes" />
			<feat att="joiningElement" val="nil" />
			<feat att="joiningElementResult" val="banan" />
		</FormRepresentation>
	</Lemma>
	<WordForm>
		<feat att="grammaticalGender" val="commonGender" />
		<feat att="definiteness" val="indefinite" />
		<feat att="grammaticalNumber" val="singular" />
		<feat att="case" val="unspecified" />
		<FormRepresentation>
			<feat att="writtenForm" val="banan" />
			<feat att="inflectionalParadigm" val="MFG0016" />
			<feat att="officiallyApproved" val="yes" />
			<feat att="frequency" val="2.2857" />
		</FormRepresentation>
	</WordForm>
	<WordForm>
		<feat att="grammaticalGender" val="commonGender" />
		<feat att="definiteness" val="indefinite" />
		<feat att="grammaticalNumber" val="singular" />
		<feat att="case" val="genitiveCase" />
		<FormRepresentation>
			<feat att="writtenForm" val="banans" />
			<feat att="inflectionalParadigm" val="MFG0016" />
			<feat att="officiallyApproved" val="yes" />
			<feat att="frequency" val=".0179" />
		</FormRepresentation>
	</WordForm>
	<WordForm>
		<feat att="grammaticalGender" val="commonGender" />
		<feat att="definiteness" val="indefinite" />
		<feat att="grammaticalNumber" val="plural" />
		<feat att="case" val="unspecified" />
		<FormRepresentation>
			<feat att="writtenForm" val="bananer" />
			<feat att="inflectionalParadigm" val="MFG0016" />
			<feat att="officiallyApproved" val="yes" />
			<feat att="frequency" val="5.625" />
		</FormRepresentation>
	</WordForm>
	<WordForm>
		<feat att="grammaticalGender" val="commonGender" />
		<feat att="definiteness" val="indefinite" />
		<feat att="grammaticalNumber" val="plural" />
		<feat att="case" val="genitiveCase" />
		<FormRepresentation>
			<feat att="writtenForm" val="bananers" />
			<feat att="inflectionalParadigm" val="MFG0016" />
			<feat att="officiallyApproved" val="yes" />
			<feat att="frequency" val=".0357" />
		</FormRepresentation>
	</WordForm>
	<WordForm>
		<feat att="grammaticalGender" val="commonGender" />
		<feat att="definiteness" val="definite" />
		<feat att="grammaticalNumber" val="singular" />
		<feat att="case" val="unspecified" />
		<FormRepresentation>
			<feat att="writtenForm" val="bananen" />
			<feat att="inflectionalParadigm" val="MFG0016" />
			<feat att="officiallyApproved" val="yes" />
			<feat att="frequency" val=".5357" />
		</FormRepresentation>
	</WordForm>
	<WordForm>
		<feat att="grammaticalGender" val="commonGender" />
		<feat att="definiteness" val="definite" />
		<feat att="grammaticalNumber" val="singular" />
		<feat att="case" val="genitiveCase" />
		<FormRepresentation>
			<feat att="writtenForm" val="bananens" />
			<feat att="inflectionalParadigm" val="MFG0016" />
			<feat att="officiallyApproved" val="yes" />
			<feat att="frequency" val=".0357" />
		</FormRepresentation>
	</WordForm>
	<WordForm>
		<feat att="grammaticalGender" val="commonGender" />
		<feat att="definiteness" val="definite" />
		<feat att="grammaticalNumber" val="plural" />
		<feat att="case" val="unspecified" />
		<FormRepresentation>
			<feat att="writtenForm" val="bananerne" />
			<feat att="inflectionalParadigm" val="MFG0016" />
			<feat att="officiallyApproved" val="yes" />
			<feat att="frequency" val=".5357" />
		</FormRepresentation>
	</WordForm>
	<WordForm>
		<feat att="grammaticalGender" val="commonGender" />
		<feat att="definiteness" val="definite" />
		<feat att="grammaticalNumber" val="plural" />
		<feat att="case" val="genitiveCase" />
		<FormRepresentation>
			<feat att="writtenForm" val="bananernes" />
			<feat att="inflectionalParadigm" val="MFG0016" />
			<feat att="officiallyApproved" val="yes" />
			<feat att="frequency" val=".0179" />
		</FormRepresentation>
	</WordForm>
</LexicalEntry>
