<LexicalEntry>
	<feat att="partOfSpeech" val="commonNoun" />
	<feat att="id" val="GMU_SANDSÆK_1" />
	<feat att="morphologicalUnitId" val="SANDSÆK" />
	<feat att="originalSource" val="PAROLE" />
	<feat att="independentWord" val="yes" />
	<feat att="decomposition" val="sand+sæk" />
	<Lemma>
		<FormRepresentation>
			<feat att="writtenForm" val="sandsæk" />
			<feat att="officiallyApproved" val="yes" />
			<feat att="joiningElement" val="Not analyzed" />
		</FormRepresentation>
	</Lemma>
	<WordForm>
		<feat att="grammaticalGender" val="commonGender" />
		<feat att="definiteness" val="indefinite" />
		<feat att="grammaticalNumber" val="singular" />
		<feat att="case" val="unspecified" />
		<FormRepresentation>
			<feat att="writtenForm" val="sandsæk" />
			<feat att="inflectionalParadigm" val="MFG0061" />
			<feat att="officiallyApproved" val="yes" />
			<feat att="frequency" val=".125" />
		</FormRepresentation>
	</WordForm>
	<WordForm>
		<feat att="grammaticalGender" val="commonGender" />
		<feat att="definiteness" val="indefinite" />
		<feat att="grammaticalNumber" val="singular" />
		<feat att="case" val="genitiveCase" />
		<FormRepresentation>
			<feat att="writtenForm" val="sandsæks" />
			<feat att="inflectionalParadigm" val="MFG0061" />
			<feat att="officiallyApproved" val="yes" />
			<feat att="frequency" val="0.0" />
		</FormRepresentation>
	</WordForm>
	<WordForm>
		<feat att="grammaticalGender" val="commonGender" />
		<feat att="definiteness" val="indefinite" />
		<feat att="grammaticalNumber" val="plural" />
		<feat att="case" val="unspecified" />
		<FormRepresentation>
			<feat att="writtenForm" val="sandsække" />
			<feat att="inflectionalParadigm" val="MFG0061" />
			<feat att="officiallyApproved" val="yes" />
			<feat att="frequency" val=".4821" />
		</FormRepresentation>
	</WordForm>
	<WordForm>
		<feat att="grammaticalGender" val="commonGender" />
		<feat att="definiteness" val="indefinite" />
		<feat att="grammaticalNumber" val="plural" />
		<feat att="case" val="genitiveCase" />
		<FormRepresentation>
			<feat att="writtenForm" val="sandsækkes" />
			<feat att="inflectionalParadigm" val="MFG0061" />
			<feat att="officiallyApproved" val="yes" />
			<feat att="frequency" val="0.0" />
		</FormRepresentation>
	</WordForm>
	<WordForm>
		<feat att="grammaticalGender" val="commonGender" />
		<feat att="definiteness" val="definite" />
		<feat att="grammaticalNumber" val="singular" />
		<feat att="case" val="unspecified" />
		<FormRepresentation>
			<feat att="writtenForm" val="sandsækken" />
			<feat att="inflectionalParadigm" val="MFG0061" />
			<feat att="officiallyApproved" val="yes" />
			<feat att="frequency" val="0.0" />
		</FormRepresentation>
	</WordForm>
	<WordForm>
		<feat att="grammaticalGender" val="commonGender" />
		<feat att="definiteness" val="definite" />
		<feat att="grammaticalNumber" val="singular" />
		<feat att="case" val="genitiveCase" />
		<FormRepresentation>
			<feat att="writtenForm" val="sandsækkens" />
			<feat att="inflectionalParadigm" val="MFG0061" />
			<feat att="officiallyApproved" val="yes" />
			<feat att="frequency" val="0.0" />
		</FormRepresentation>
	</WordForm>
	<WordForm>
		<feat att="grammaticalGender" val="commonGender" />
		<feat att="definiteness" val="definite" />
		<feat att="grammaticalNumber" val="plural" />
		<feat att="case" val="unspecified" />
		<FormRepresentation>
			<feat att="writtenForm" val="sandsækkene" />
			<feat att="inflectionalParadigm" val="MFG0061" />
			<feat att="officiallyApproved" val="yes" />
			<feat att="frequency" val=".0357" />
		</FormRepresentation>
	</WordForm>
	<WordForm>
		<feat att="grammaticalGender" val="commonGender" />
		<feat att="definiteness" val="definite" />
		<feat att="grammaticalNumber" val="plural" />
		<feat att="case" val="genitiveCase" />
		<FormRepresentation>
			<feat att="writtenForm" val="sandsækkenes" />
			<feat att="inflectionalParadigm" val="MFG0061" />
			<feat att="officiallyApproved" val="yes" />
			<feat att="frequency" val="0.0" />
		</FormRepresentation>
	</WordForm>
</LexicalEntry>
