<LexicalEntry>
	<feat att="partOfSpeech" val="commonNoun" />
	<feat att="id" val="GMU_KANVAS,1_2" />
	<feat att="morphologicalUnitId" val="KANVAS_1" />
	<feat att="originalSource" val="UKENDT" />
	<feat att="independentWord" val="yes" />
	<Lemma>
		<FormRepresentation>
			<feat att="writtenForm" val="kanvas" />
			<feat att="officiallyApproved" val="yes" />
			<feat att="joiningElement" val="Not analyzed" />
		</FormRepresentation>
	</Lemma>
	<WordForm>
		<feat att="grammaticalGender" val="neuter" />
		<feat att="definiteness" val="indefinite" />
		<feat att="grammaticalNumber" val="singular" />
		<feat att="case" val="unspecified" />
		<FormRepresentation>
			<feat att="writtenForm" val="kanvas" />
			<feat att="inflectionalParadigm" val="MFG0284" />
			<feat att="officiallyApproved" val="yes" />
			<feat att="frequency" val=".1786" />
		</FormRepresentation>
	</WordForm>
	<WordForm>
		<feat att="grammaticalGender" val="neuter" />
		<feat att="definiteness" val="indefinite" />
		<feat att="grammaticalNumber" val="singular" />
		<feat att="case" val="genitiveCase" />
		<FormRepresentation>
			<feat att="writtenForm" val="kanvases" />
			<feat att="inflectionalParadigm" val="MFG0265,MFG0284" />
			<feat att="officiallyApproved" val="no" />
			<feat att="frequency" val="0.0" />
		</FormRepresentation>
		<FormRepresentation>
			<feat att="writtenForm" val="kanvas's" />
			<feat att="inflectionalParadigm" val="MFG0265,MFG0284" />
			<feat att="officiallyApproved" val="no" />
			<feat att="frequency" val="0.0" />
		</FormRepresentation>
		<FormRepresentation>
			<feat att="writtenForm" val="kanvas'" />
			<feat att="inflectionalParadigm" val="MFG0284" />
			<feat att="officiallyApproved" val="yes" />
			<feat att="frequency" val="0.0" />
		</FormRepresentation>
	</WordForm>
	<WordForm>
		<feat att="grammaticalGender" val="neuter" />
		<feat att="definiteness" val="definite" />
		<feat att="grammaticalNumber" val="singular" />
		<feat att="case" val="unspecified" />
		<FormRepresentation>
			<feat att="writtenForm" val="kanvasset" />
			<feat att="inflectionalParadigm" val="MFG0284" />
			<feat att="officiallyApproved" val="yes" />
			<feat att="frequency" val="0.0" />
		</FormRepresentation>
		<FormRepresentation>
			<feat att="writtenForm" val="kanvaset" />
			<feat att="inflectionalParadigm" val="MFG0265" />
			<feat att="officiallyApproved" val="no" />
			<feat att="frequency" val="0.0" />
		</FormRepresentation>
	</WordForm>
	<WordForm>
		<feat att="grammaticalGender" val="neuter" />
		<feat att="definiteness" val="definite" />
		<feat att="grammaticalNumber" val="singular" />
		<feat att="case" val="genitiveCase" />
		<FormRepresentation>
			<feat att="writtenForm" val="kanvassets" />
			<feat att="inflectionalParadigm" val="MFG0284" />
			<feat att="officiallyApproved" val="yes" />
			<feat att="frequency" val="0.0" />
		</FormRepresentation>
		<FormRepresentation>
			<feat att="writtenForm" val="kanvasets" />
			<feat att="inflectionalParadigm" val="MFG0265" />
			<feat att="officiallyApproved" val="no" />
			<feat att="frequency" val="0.0" />
		</FormRepresentation>
	</WordForm>
	<WordForm>
		<feat att="grammaticalGender" val="commonGender" />
		<feat att="definiteness" val="indefinite" />
		<feat att="grammaticalNumber" val="singular" />
		<feat att="case" val="unspecified" />
		<FormRepresentation>
			<feat att="writtenForm" val="kanvas" />
			<feat att="inflectionalParadigm" val="MFG0272" />
			<feat att="officiallyApproved" val="yes" />
			<feat att="frequency" val=".1786" />
		</FormRepresentation>
	</WordForm>
	<WordForm>
		<feat att="grammaticalGender" val="commonGender" />
		<feat att="definiteness" val="indefinite" />
		<feat att="grammaticalNumber" val="singular" />
		<feat att="case" val="genitiveCase" />
		<FormRepresentation>
			<feat att="writtenForm" val="kanvases" />
			<feat att="inflectionalParadigm" val="MFG0236,MFG0272" />
			<feat att="officiallyApproved" val="no" />
			<feat att="frequency" val="0.0" />
		</FormRepresentation>
		<FormRepresentation>
			<feat att="writtenForm" val="kanvas's" />
			<feat att="inflectionalParadigm" val="MFG0236,MFG0272" />
			<feat att="officiallyApproved" val="no" />
			<feat att="frequency" val="0.0" />
		</FormRepresentation>
		<FormRepresentation>
			<feat att="writtenForm" val="kanvas'" />
			<feat att="inflectionalParadigm" val="MFG0272" />
			<feat att="officiallyApproved" val="yes" />
			<feat att="frequency" val="0.0" />
		</FormRepresentation>
	</WordForm>
	<WordForm>
		<feat att="grammaticalGender" val="commonGender" />
		<feat att="definiteness" val="definite" />
		<feat att="grammaticalNumber" val="singular" />
		<feat att="case" val="unspecified" />
		<FormRepresentation>
			<feat att="writtenForm" val="kanvassen" />
			<feat att="inflectionalParadigm" val="MFG0272" />
			<feat att="officiallyApproved" val="yes" />
			<feat att="frequency" val=".3393" />
		</FormRepresentation>
		<FormRepresentation>
			<feat att="writtenForm" val="kanvasen" />
			<feat att="inflectionalParadigm" val="MFG0236" />
			<feat att="officiallyApproved" val="no" />
			<feat att="frequency" val="0.0" />
		</FormRepresentation>
	</WordForm>
	<WordForm>
		<feat att="grammaticalGender" val="commonGender" />
		<feat att="definiteness" val="definite" />
		<feat att="grammaticalNumber" val="singular" />
		<feat att="case" val="genitiveCase" />
		<FormRepresentation>
			<feat att="writtenForm" val="kanvassens" />
			<feat att="inflectionalParadigm" val="MFG0272" />
			<feat att="officiallyApproved" val="yes" />
			<feat att="frequency" val="0.0" />
		</FormRepresentation>
		<FormRepresentation>
			<feat att="writtenForm" val="kanvasens" />
			<feat att="inflectionalParadigm" val="MFG0236" />
			<feat att="officiallyApproved" val="no" />
			<feat att="frequency" val="0.0" />
		</FormRepresentation>
	</WordForm>
	<RelatedForm>
		<feat att="spellingVariant" val="GMU_KANVAS,1_1" />
		<FormRepresentation>
			<feat att="writtenForm" val="kannevas" />
		</FormRepresentation>
	</RelatedForm>
</LexicalEntry>
