<LexicalEntry>
	<feat att="partOfSpeech" val="commonNoun" />
	<feat att="id" val="GMU_KATASTROFEVALG_1" />
	<feat att="morphologicalUnitId" val="KATASTROFEVALG" />
	<feat att="originalSource" val="DDO" />
	<feat att="independentWord" val="yes" />
	<feat att="decomposition" val="katastrofe+valg" />
	<Lemma>
		<FormRepresentation>
			<feat att="writtenForm" val="katastrofevalg" />
			<feat att="officiallyApproved" val="yes" />
			<feat att="joiningElement" val="Not analyzed" />
		</FormRepresentation>
	</Lemma>
	<WordForm>
		<feat att="grammaticalGender" val="neuter" />
		<feat att="definiteness" val="indefinite" />
		<feat att="grammaticalNumber" val="singular" />
		<feat att="case" val="unspecified" />
		<FormRepresentation>
			<feat att="writtenForm" val="katastrofevalg" />
			<feat att="inflectionalParadigm" val="MFG0040" />
			<feat att="officiallyApproved" val="yes" />
			<feat att="frequency" val=".2143" />
		</FormRepresentation>
	</WordForm>
	<WordForm>
		<feat att="grammaticalGender" val="neuter" />
		<feat att="definiteness" val="indefinite" />
		<feat att="grammaticalNumber" val="singular" />
		<feat att="case" val="genitiveCase" />
		<FormRepresentation>
			<feat att="writtenForm" val="katastrofevalgs" />
			<feat att="inflectionalParadigm" val="MFG0040" />
			<feat att="officiallyApproved" val="yes" />
			<feat att="frequency" val="0.0" />
		</FormRepresentation>
	</WordForm>
	<WordForm>
		<feat att="grammaticalGender" val="neuter" />
		<feat att="definiteness" val="indefinite" />
		<feat att="grammaticalNumber" val="plural" />
		<feat att="case" val="unspecified" />
		<FormRepresentation>
			<feat att="writtenForm" val="katastrofevalg" />
			<feat att="inflectionalParadigm" val="MFG0040" />
			<feat att="officiallyApproved" val="yes" />
			<feat att="frequency" val=".2143" />
		</FormRepresentation>
	</WordForm>
	<WordForm>
		<feat att="grammaticalGender" val="neuter" />
		<feat att="definiteness" val="indefinite" />
		<feat att="grammaticalNumber" val="plural" />
		<feat att="case" val="genitiveCase" />
		<FormRepresentation>
			<feat att="writtenForm" val="katastrofevalgs" />
			<feat att="inflectionalParadigm" val="MFG0040" />
			<feat att="officiallyApproved" val="yes" />
			<feat att="frequency" val="0.0" />
		</FormRepresentation>
	</WordForm>
	<WordForm>
		<feat att="grammaticalGender" val="neuter" />
		<feat att="definiteness" val="definite" />
		<feat att="grammaticalNumber" val="singular" />
		<feat att="case" val="unspecified" />
		<FormRepresentation>
			<feat att="writtenForm" val="katastrofevalget" />
			<feat att="inflectionalParadigm" val="MFG0040" />
			<feat att="officiallyApproved" val="yes" />
			<feat att="frequency" val=".1429" />
		</FormRepresentation>
	</WordForm>
	<WordForm>
		<feat att="grammaticalGender" val="neuter" />
		<feat att="definiteness" val="definite" />
		<feat att="grammaticalNumber" val="singular" />
		<feat att="case" val="genitiveCase" />
		<FormRepresentation>
			<feat att="writtenForm" val="katastrofevalgets" />
			<feat att="inflectionalParadigm" val="MFG0040" />
			<feat att="officiallyApproved" val="yes" />
			<feat att="frequency" val="0.0" />
		</FormRepresentation>
	</WordForm>
	<WordForm>
		<feat att="grammaticalGender" val="neuter" />
		<feat att="definiteness" val="definite" />
		<feat att="grammaticalNumber" val="plural" />
		<feat att="case" val="unspecified" />
		<FormRepresentation>
			<feat att="writtenForm" val="katastrofevalgene" />
			<feat att="inflectionalParadigm" val="MFG0040" />
			<feat att="officiallyApproved" val="yes" />
			<feat att="frequency" val="0.0" />
		</FormRepresentation>
	</WordForm>
	<WordForm>
		<feat att="grammaticalGender" val="neuter" />
		<feat att="definiteness" val="definite" />
		<feat att="grammaticalNumber" val="plural" />
		<feat att="case" val="genitiveCase" />
		<FormRepresentation>
			<feat att="writtenForm" val="katastrofevalgenes" />
			<feat att="inflectionalParadigm" val="MFG0040" />
			<feat att="officiallyApproved" val="yes" />
			<feat att="frequency" val="0.0" />
		</FormRepresentation>
	</WordForm>
</LexicalEntry>
