<LexicalEntry>
	<feat att="partOfSpeech" val="commonNoun" />
	<feat att="id" val="GMU_nærtliggende_1" />
	<feat att="morphologicalUnitId" val="NÆRTLIGGENDE" />
	<feat att="originalSource" val="DDO" />
	<feat att="independentWord" val="yes" />
	<Lemma>
		<FormRepresentation>
			<feat att="writtenForm" val="nærtliggende" />
			<feat att="officiallyApproved" val="yes" />
			<feat att="joiningElement" val="Not analyzed" />
		</FormRepresentation>
	</Lemma>
	<WordForm>
		<FormRepresentation>
			<feat att="writtenForm" val="nærtliggende" />
			<feat att="inflectionalParadigm" val="MFG1033" />
			<feat att="officiallyApproved" val="yes" />
			<feat att="frequency" val=".1786" />
		</FormRepresentation>
	</WordForm>
</LexicalEntry>
